bp_apollo_client/__init__.py
bp_apollo_client/apollo_client.py
bp_apollo_client-0.0.6.dist-info/LICENSE
bp_apollo_client-0.0.6.dist-info/METADATA
bp_apollo_client-0.0.6.dist-info/WHEEL
bp_apollo_client-0.0.6.dist-info/top_level.txt
bp_apollo_client-0.0.6.dist-info/RECORD
