Metadata-Version: 2.1
Name: bp-apollo-client
Version: 0.0.6
Summary: bp-apollo-client
Home-page: https://github.com/foxliu/pyapollo.git
Author: foxliu
Author-email: foxliu2012@gmail.com
License: UNKNOWN
Platform: any
Classifier: Programming Language :: Python :: 3.7
Requires-Python: >=3.7
License-File: LICENSE
